digital_design_samir/chapter05/D.v
module D(out,a,b,c);

//Ports
output out;
input a,b,c;

//Internal nets
wire e;

//Instantiations primitives
and #(5)(e,a,b);
or #(4)(out,e,c);

endmodule

digital_design_samir/chapter05/tb_D.v
module tb_D;

reg a,b,c;
wire out;


//instantiation
D D1(out,a,b,c);

//start monitoring
	initial
		begin
			$monitor($time," --- a=%b b=%b c=%b --- out=%b",a,b,c,out);
		end

//gtkwave 
	initial
	 begin
    $dumpfile("tb_D.vcd");
    $dumpvars(0,tb_D);
	 end

	//stimulate inputs
	initial
		begin
			a=1'b0;b=1'b0;c=1'b0;
			#10 a=1'b1;b=1'b1;c=1'b1;
			#10 a=1'b0;b=1'b1;c=1'b0;
			#20 $finish;
	

		end


endmodule

digital_design_samir/chapter05/tb_D.vcd
$date
	Mon Feb 19 14:51:14 2018
$end
$version
	Icarus Verilog
$end
$timescale
	1s
$end
$scope module tb_D $end
$var wire 1 ! out $end
$var reg 1 " a $end
$var reg 1 # b $end
$var reg 1 $ c $end
$scope module D1 $end
$var wire 1 " a $end
$var wire 1 # b $end
$var wire 1 $ c $end
$var wire 1 % e $end
$var wire 1 ! out $end
$upscope $end
$upscope $end
$enddefinitions $end
#0
$dumpvars
x%
0$
0#
0"
x!
$end
#5
0%
#9
0!
#10
1$
1#
1"
#14
1!
#15
1%
#20
0$
0"
#25
0%
#29
0!
