digital_design_samir/chapter05/latch.v
module latch(q,qbar,reset,set);
	output q,qbar;
	input reset,set;

	//instantiate primitives
	nor #(1)(q,reset,qbar);
	nor #(1)(qbar,set,q);



endmodule

digital_design_samir/chapter05/tb_latch.v
module tb_latch;

	reg RESET,SET;
	wire Q,QBAR;

	//initialize module
	latch l1(Q,QBAR,RESET,SET);

	//monitoring
	initial
		begin
			$monitor($time," set=%b reset=%b q=%b notq=%b",SET,RESET,Q,QBAR);
		end

	//gtkwave 
	initial
	 begin
    $dumpfile("tb_latch.vcd");
    $dumpvars(0,tb_latch);
	 end


	//stimulus
	// comment 
	// 		tb_latch has 2 nor primitives with each #1 delay. 
	// 		to get a stabilized result, you have to wait #2 periods
	initial
		begin
			SET=1'b0;RESET=1'b0;
			#2 SET=1'b1;RESET=1'b0;
			#2 SET=1'b0;RESET=1'b0;
			#2 SET=1'b0;RESET=1'b0;
			#2 SET=1'b0;RESET=1'b0;
			#2 SET=1'b0;RESET=1'b1;
			#2 SET=1'b0;RESET=1'b0;
			#2 SET=1'b0;RESET=1'b0;
			#2 SET=1'b0;RESET=1'b0;
			#2 SET=1'b0;RESET=1'b1;
			#2 SET=1'b0;RESET=1'b0;
			#2 SET=1'b0;RESET=1'b0;
			#2 SET=1'b1;RESET=1'b0;
			#2 SET=1'b0;RESET=1'b0;
			#2 $finish;

			
			
		end


endmodule

digital_design_samir/chapter05/tb_latch.vcd
$date
	Wed Feb 21 14:54:24 2018
$end
$version
	Icarus Verilog
$end
$timescale
	1s
$end
$scope module tb_latch $end
$var wire 1 ! QBAR $end
$var wire 1 " Q $end
$var reg 1 # RESET $end
$var reg 1 $ SET $end
$scope module l1 $end
$var wire 1 " q $end
$var wire 1 ! qbar $end
$var wire 1 # reset $end
$var wire 1 $ set $end
$upscope $end
$upscope $end
$enddefinitions $end
#0
$dumpvars
0$
0#
x"
x!
$end
#2
1$
#3
0!
#4
1"
0$
#10
1#
#11
0"
#12
1!
0#
#18
1#
#20
0#
#24
1$
#25
0!
#26
1"
0$
