digital_design_samir/chapter05/mux2to1.v
module mux2to1(out,in0,in1,s);

//ports
output out;
input in0,in1,s;

//instantiation primitives
bufif1 #(1:2:3,3:4:5,5:6:7)(out,in0,s);
bufif0 #(1:2:3,3:4:5,5:6:7)(out,in1,s);

endmodule

digital_design_samir/chapter05/tb_mux2to1.v
module tb_mux2to1;
	reg IN0,IN1,S;
	wire out;

	//instantiation
	mux2to1 m1(OUT,IN0,IN1,S);

	//monitoring
	initial
		begin
			$monitor($time,"IN0=%b IN1=%b S=%b OUT=%b",IN0,IN1,S,OUT);
		end

	//gtkwave
	initial
		begin
			$dumpfile("tb_mux2to1.vcd");
			$dumpvars(0,tb_mux2to1);
		end


	//stimulus
	initial
		begin
			IN0=1'b0;IN1=1'b0;S=1'b0;
			#10 IN0=1'b0;IN1=1'b0;S=1'b1;
			#10 IN0=1'b0;IN1=1'b1;S=1'b0;
			#10 IN0=1'b0;IN1=1'b1;S=1'b1;
			#10 IN0=1'b1;IN1=1'b0;S=1'b0;
			#10 IN0=1'b1;IN1=1'b0;S=1'b1;
			#10 IN0=1'b1;IN1=1'b1;S=1'b0;
			#10 IN0=1'b1;IN1=1'b1;S=1'b1;


		end


endmodule

digital_design_samir/chapter05/tb_mux2to1.vcd
$date
	Mon Feb 26 12:58:29 2018
$end
$version
	Icarus Verilog
$end
$timescale
	1s
$end
$scope module tb_mux2to1 $end
$var wire 1 ! OUT $end
$var reg 1 " IN0 $end
$var reg 1 # IN1 $end
$var reg 1 $ S $end
$scope module m1 $end
$var wire 1 " in0 $end
$var wire 1 # in1 $end
$var wire 1 ! out $end
$var wire 1 $ s $end
$upscope $end
$upscope $end
$enddefinitions $end
#0
$dumpvars
0$
0#
0"
x!
$end
#4
0!
#10
1$
#20
0$
1#
#22
x!
#26
1!
#30
1$
#34
x!
#36
0!
#40
0$
0#
1"
#50
1$
#52
x!
#56
1!
#60
0$
1#
#70
1$
